{
  "dependencies": [
    {
      "name": "@types/node",
      "version": "^12",
      "type": "build"
    },
    {
      "name": "@types/react",
      "type": "build"
    },
    {
      "name": "@types/react-dom",
      "type": "build"
    },
    {
      "name": "npm-check-updates",
      "version": "^16",
      "type": "build"
    },
    {
      "name": "projen",
      "type": "build"
    },
    {
      "name": "typescript",
      "type": "build"
    },
    {
      "name": "@next/font",
      "type": "runtime"
    },
    {
      "name": "autoprefixer",
      "type": "runtime"
    },
    {
      "name": "next",
      "type": "runtime"
    },
    {
      "name": "postcss",
      "type": "runtime"
    },
    {
      "name": "react",
      "type": "runtime"
    },
    {
      "name": "react-dom",
      "type": "runtime"
    },
    {
      "name": "swr",
      "type": "runtime"
    },
    {
      "name": "tailwindcss",
      "type": "runtime"
    }
  ],
  "//": "~~ Generated by projen. To modify, edit .projenrc.js and run \"npx projen\"."
}
